topsis/__init__.py
topsis/topsis.py
topsis_ANMOL_BHATT_102217006-1.0.4.dist-info/LICENSE.txt
topsis_ANMOL_BHATT_102217006-1.0.4.dist-info/METADATA
topsis_ANMOL_BHATT_102217006-1.0.4.dist-info/WHEEL
topsis_ANMOL_BHATT_102217006-1.0.4.dist-info/entry_points.txt
topsis_ANMOL_BHATT_102217006-1.0.4.dist-info/top_level.txt
topsis_ANMOL_BHATT_102217006-1.0.4.dist-info/RECORD
