Metadata-Version: 2.2
Name: topsis-ANMOL-BHATT-102217006
Version: 1.0.4
Summary: A Python package for implementing the TOPSIS multi-criteria decision analysis method.
Author: ANMOL BHATT
License: MIT
Classifier: Programming Language :: Python :: 3
Classifier: License :: OSI Approved :: MIT License
Classifier: Operating System :: OS Independent
Requires-Python: >=3.6
License-File: LICENSE.txt
Requires-Dist: numpy
Requires-Dist: pandas
Dynamic: author
Dynamic: classifier
Dynamic: description
Dynamic: description-content-type
Dynamic: license
Dynamic: requires-dist
Dynamic: requires-python
Dynamic: summary
